{
  "2025": {
    "gameName": "REEFSCAPE",
    "scoring": {
      "autonomous": {
        "leave": {
          "label": "Leave Starting Zone",
          "points": 3,
          "description": "Robot leaves starting zone during autonomous",
          "type": "boolean"
        },
        "L1_coral": {
          "label": "L1 Coral (Auto)",
          "points": 3,
          "description": "Coral scored in trough (L1) during autonomous"
        },
        "L2_coral": {
          "label": "L2 Coral (Auto)",
          "points": 4,
          "description": "Coral scored on L2 branch during autonomous"
        },
        "L3_coral": {
          "label": "L3 Coral (Auto)",
          "points": 6,
          "description": "Coral scored on L3 branch during autonomous"
        },
        "L4_coral": {
          "label": "L4 Coral (Auto)",
          "points": 7,
          "description": "Coral scored on L4 branch during autonomous"
        },
        "processor_algae": {
          "label": "Processor Algae (Auto)",
          "points": 6,
          "description": "Algae scored in processor during autonomous"
        },
        "net_algae": {
          "label": "Net Algae (Auto)",
          "points": 4,
          "description": "Algae scored in net during autonomous"
        }
      },
      "teleop": {
        "L1_coral": {
          "label": "L1 Coral (Teleop)",
          "points": 2,
          "description": "Coral scored in trough (L1) during teleoperated"
        },
        "L2_coral": {
          "label": "L2 Coral (Teleop)",
          "points": 3,
          "description": "Coral scored on L2 branch during teleoperated"
        },
        "L3_coral": {
          "label": "L3 Coral (Teleop)",
          "points": 4,
          "description": "Coral scored on L3 branch during teleoperated"
        },
        "L4_coral": {
          "label": "L4 Coral (Teleop)",
          "points": 5,
          "description": "Coral scored on L4 branch during teleoperated"
        },
        "processor_algae": {
          "label": "Processor Algae (Teleop)",
          "points": 6,
          "description": "Algae scored in processor during teleoperated"
        },
        "net_algae": {
          "label": "Net Algae (Teleop)",
          "points": 4,
          "description": "Algae scored in net during teleoperated"
        }
      },
      "endgame": {
        "ending_robot_state": {
          "label": "Ending Robot State",
          "description": "Robot's final position during endgame",
          "pointValues": {
            "none": 0,
            "park": 3,
            "shallow": 6,
            "deep": 12
          }
        }
      },
      "fouls": {
        "fouls": {
          "label": "Fouls",
          "points": -2,
          "description": "Minor penalties committed"
        },
        "tech_fouls": {
          "label": "Tech Fouls",
          "points": -5,
          "description": "Technical fouls committed"
        }
      }
    },
    "pitScouting": {
      "customFields": [
        {
          "name": "coralCapability",
          "label": "Coral Scoring Capability",
          "type": "select",
          "options": ["L1 only", "L1-L2", "L1-L3", "L1-L4", "L2-L4", "None"]
        },
        {
          "name": "algaeCapability",
          "label": "Algae Scoring Capability",
          "type": "select",
          "options": ["Net only", "Processor only", "Both", "Neither"]
        },
        {
          "name": "intakeType",
          "label": "Intake Method",
          "type": "select",
          "options": ["Ground pickup", "Human player", "Both", "Neither"]
        },
        {
          "name": "climbCapability",
          "label": "Climbing Capability",
          "type": "select",
          "options": ["No climb", "Shallow cage only", "Deep cage only", "Both cages"]
        },
        {
          "name": "autoCapability",
          "label": "Autonomous Capability",
          "type": "select",
          "options": ["Leave only", "Leave + Score", "Complex auto", "None"]
        },
        {
          "name": "cycleTime",
          "label": "Estimated Cycle Time (seconds)",
          "type": "number"
        },
        {
          "name": "reliability",
          "label": "Robot Reliability",
          "type": "select",
          "options": ["Very Reliable", "Mostly Reliable", "Somewhat Reliable", "Unreliable"]
        }
      ]
    }
  },
  "2024": {
    "gameName": "CRESCENDO",
    "scoring": {
      "autonomous": {
        "Speaker": {
          "label": "Speaker (Auto)",
          "points": 5,
          "description": "Notes scored in Speaker during autonomous"
        },
        "Amp": {
          "label": "Amp (Auto)",
          "points": 2,
          "description": "Notes scored in Amp during autonomous"
        },
        "mobility": {
          "label": "Mobility",
          "points": 2,
          "description": "Robot leaves starting zone during autonomous",
          "type": "boolean"
        }
      },
      "teleop": {
        "Speaker": {
          "label": "Speaker (Teleop)",
          "points": 2,
          "description": "Notes scored in Speaker during teleoperated"
        },
        "Amp": {
          "label": "Amp (Teleop)",
          "points": 1,
          "description": "Notes scored in Amp during teleoperated"
        },
        "Trap": {
          "label": "Trap",
          "points": 5,
          "description": "Notes scored in Trap"
        }
      },
      "endgame": {
        "climbState": {
          "label": "Climb State",
          "description": "Robot's final position during endgame",
          "pointValues": {
            "park": 1,
            "onstage": 3,
            "none": 0
          }
        },
        "harmony": {
          "label": "Harmony",
          "points": 2,
          "description": "Multiple robots on stage (team bonus)",
          "type": "boolean"
        }
      }
    },
    "pitScouting": {
      "customFields": [
        {
          "name": "shootingRange",
          "label": "Shooting Range",
          "type": "select",
          "options": ["Contact", "Short", "Medium", "Long", "Variable"]
        },
        {
          "name": "intakeCapability",
          "label": "Intake Capability",
          "type": "select",
          "options": ["Ground only", "Source only", "Both", "Neither"]
        },
        {
          "name": "climbCapability",
          "label": "Climbing Capability",
          "type": "boolean"
        },
        {
          "name": "cycleTime",
          "label": "Estimated Cycle Time (seconds)",
          "type": "number"
        }
      ]
    }
  },
  "2023": {
    "gameName": "CHARGED UP",
    "scoring": {
      "autonomous": {
        "Cones": {
          "label": "Cones (Auto)",
          "points": 6,
          "description": "Cones scored during autonomous"
        },
        "Cubes": {
          "label": "Cubes (Auto)",
          "points": 6,
          "description": "Cubes scored during autonomous"
        },
        "mobility": {
          "label": "Mobility",
          "points": 3,
          "description": "Robot leaves community during autonomous",
          "type": "boolean"
        },
        "docking": {
          "label": "Auto Docking",
          "points": 8,
          "description": "Robot docks during autonomous",
          "type": "boolean"
        },
        "engaging": {
          "label": "Auto Engaging",
          "points": 12,
          "description": "Robot engages charge station during autonomous",
          "type": "boolean"
        }
      },
      "teleop": {
        "Cones": {
          "label": "Cones (Teleop)",
          "points": 5,
          "description": "Cones scored during teleoperated"
        },
        "Cubes": {
          "label": "Cubes (Teleop)",
          "points": 3,
          "description": "Cubes scored during teleoperated"
        }
      },
      "endgame": {
        "park": {
          "label": "Park",
          "points": 2,
          "description": "Robot parked in community",
          "type": "boolean"
        },
        "docking": {
          "label": "Docking",
          "points": 6,
          "description": "Robot docks on charge station",
          "type": "boolean"
        },
        "engaging": {
          "label": "Engaging",
          "points": 10,
          "description": "Robot engages charge station",
          "type": "boolean"
        }
      }
    },
    "pitScouting": {
      "customFields": [
        {
          "name": "gamePiecePreference",
          "label": "Game Piece Preference",
          "type": "select",
          "options": ["Cones only", "Cubes only", "Both", "Neither"]
        },
        {
          "name": "scoringLevels",
          "label": "Scoring Levels",
          "type": "select",
          "options": ["Hybrid only", "Mid only", "High only", "Multiple"]
        },
        {
          "name": "balanceCapability",
          "label": "Balance Capability",
          "type": "boolean"
        },
        {
          "name": "cycleTime",
          "label": "Estimated Cycle Time (seconds)",
          "type": "number"
        }
      ]
    }
  }
}
